cyberfusion/PagerDutyVoysWebhook/__init__.py
cyberfusion/PagerDutyVoysWebhook/api.py
cyberfusion/PagerDutyVoysWebhook/pagerduty.py
cyberfusion/PagerDutyVoysWebhook/settings.py
cyberfusion/PagerDutyVoysWebhook/voys.py
python3_cyberfusion_pagerduty_voys_webhook-1.2.dist-info/METADATA
python3_cyberfusion_pagerduty_voys_webhook-1.2.dist-info/WHEEL
python3_cyberfusion_pagerduty_voys_webhook-1.2.dist-info/top_level.txt
python3_cyberfusion_pagerduty_voys_webhook-1.2.dist-info/RECORD
