Metadata-Version: 2.4
Name: python3-cyberfusion-pagerduty-voys-webhook
Version: 1.2
Summary: Webhook server to dynamically route Voys calls to on-call PagerDuty users.
Author-email: Cyberfusion <support@cyberfusion.io>
Project-URL: Source, https://github.com/CyberfusionIO/python3-cyberfusion-pagerduty-voys-webhook
Requires-Dist: fastapi==0.115.11
Requires-Dist: requests==2.32.3
Requires-Dist: pydantic-settings==2.8.1
